{
	"id": "0NsjJAcR1squnmh",
	"json": "{\"id\":\"0NsjJAcR1squnmh\",\"url\":\"https://gsalr.com/garage-sales-in/nevada/page/2/\",\"uniqueKey\":\"https://gsalr.com/garage-sales-in/nevada/page/2\",\"method\":\"GET\",\"noRetry\":false,\"retryCount\":0,\"errorMessages\":[],\"headers\":{},\"userData\":{\"source\":\"gsalr\",\"state\":\"nevada\",\"pageType\":\"index\"}}",
	"method": "GET",
	"orderNo": 1777040334415,
	"retryCount": 0,
	"uniqueKey": "https://gsalr.com/garage-sales-in/nevada/page/2",
	"url": "https://gsalr.com/garage-sales-in/nevada/page/2/"
}