{
	"id": "2p4sr19Iz0x23NY",
	"json": "{\"id\":\"2p4sr19Iz0x23NY\",\"url\":\"https://yardsaletreasuremap.com/US/Tennessee/\",\"uniqueKey\":\"https://yardsaletreasuremap.com/US/Tennessee\",\"method\":\"GET\",\"noRetry\":false,\"retryCount\":0,\"errorMessages\":[],\"headers\":{},\"userData\":{\"source\":\"ystm\",\"state\":\"Tennessee\"}}",
	"method": "GET",
	"orderNo": 1777186533378,
	"retryCount": 0,
	"uniqueKey": "https://yardsaletreasuremap.com/US/Tennessee",
	"url": "https://yardsaletreasuremap.com/US/Tennessee/"
}