{
	"id": "36KWdw1p5y0C6O8",
	"json": "{\"id\":\"36KWdw1p5y0C6O8\",\"url\":\"https://odessa.craigslist.org/search/sss?query=yard+sale+garage+sale&s=480\",\"uniqueKey\":\"https://odessa.craigslist.org/search/sss?query=yard+sale+garage+sale&s=480\",\"method\":\"GET\",\"noRetry\":false,\"retryCount\":0,\"errorMessages\":[],\"headers\":{},\"userData\":{\"source\":\"craigslist\",\"state\":\"TX\"}}",
	"method": "GET",
	"orderNo": 1777186526385,
	"retryCount": 0,
	"uniqueKey": "https://odessa.craigslist.org/search/sss?query=yard+sale+garage+sale&s=480",
	"url": "https://odessa.craigslist.org/search/sss?query=yard+sale+garage+sale&s=480"
}