{
	"id": "5U5y89b6LaDJS6o",
	"json": "{\"id\":\"5U5y89b6LaDJS6o\",\"url\":\"https://fortcollins.craigslist.org/search/sss?query=moving+sale\",\"loadedUrl\":\"https://fortcollins.craigslist.org/search/sss?query=moving+sale\",\"uniqueKey\":\"https://fortcollins.craigslist.org/search/sss?query=moving+sale\",\"method\":\"GET\",\"noRetry\":false,\"retryCount\":0,\"errorMessages\":[],\"headers\":{},\"userData\":{\"source\":\"craigslist\",\"state\":\"CO\",\"__crawlee\":{\"state\":4}},\"handledAt\":\"2026-04-26T12:50:28.671Z\"}",
	"method": "GET",
	"orderNo": null,
	"retryCount": 0,
	"uniqueKey": "https://fortcollins.craigslist.org/search/sss?query=moving+sale",
	"url": "https://fortcollins.craigslist.org/search/sss?query=moving+sale"
}