{
	"id": "6CHz8SgF8cIcnan",
	"json": "{\"id\":\"6CHz8SgF8cIcnan\",\"url\":\"https://www.yardsalesearch.com/garage-sales-in-Rockford-IL.html?page=3\",\"uniqueKey\":\"https://www.yardsalesearch.com/garage-sales-in-Rockford-IL.html?page=3\",\"method\":\"GET\",\"noRetry\":false,\"retryCount\":0,\"errorMessages\":[],\"headers\":{},\"userData\":{\"source\":\"yardsalesearch\",\"state\":\"IL\",\"pageType\":\"index\"}}",
	"method": "GET",
	"orderNo": 1777040331983,
	"retryCount": 0,
	"uniqueKey": "https://www.yardsalesearch.com/garage-sales-in-Rockford-IL.html?page=3",
	"url": "https://www.yardsalesearch.com/garage-sales-in-Rockford-IL.html?page=3"
}