{
	"id": "7dfPGjc2BhvmnB9",
	"json": "{\"id\":\"7dfPGjc2BhvmnB9\",\"url\":\"https://www.estatesales.net/Wyoming?page=3\",\"uniqueKey\":\"https://www.estatesales.net/Wyoming?page=3\",\"method\":\"GET\",\"noRetry\":false,\"retryCount\":0,\"errorMessages\":[],\"headers\":{},\"userData\":{\"source\":\"estatesales\",\"state\":\"Wyoming\",\"pageType\":\"index\"}}",
	"method": "GET",
	"orderNo": 1777040330163,
	"retryCount": 0,
	"uniqueKey": "https://www.estatesales.net/Wyoming?page=3",
	"url": "https://www.estatesales.net/Wyoming?page=3"
}