{
	"id": "99yphqlCwrAVjfK",
	"json": "{\"id\":\"99yphqlCwrAVjfK\",\"url\":\"https://www.estatesales.net/Nevada\",\"uniqueKey\":\"https://www.estatesales.net/Nevada\",\"method\":\"GET\",\"noRetry\":false,\"retryCount\":0,\"errorMessages\":[],\"headers\":{},\"userData\":{\"source\":\"estatesales\",\"state\":\"Nevada\",\"pageType\":\"index\"}}",
	"method": "GET",
	"orderNo": 1776804010498,
	"retryCount": 0,
	"uniqueKey": "https://www.estatesales.net/Nevada",
	"url": "https://www.estatesales.net/Nevada"
}