{
	"id": "a2n60iUwmxo5zPO",
	"json": "{\"id\":\"a2n60iUwmxo5zPO\",\"url\":\"https://skagit.craigslist.org/search/sss?query=yard+sale+garage+sale&s=480\",\"uniqueKey\":\"https://skagit.craigslist.org/search/sss?query=yard+sale+garage+sale&s=480\",\"method\":\"GET\",\"noRetry\":false,\"retryCount\":0,\"errorMessages\":[],\"headers\":{},\"userData\":{\"source\":\"craigslist\",\"state\":\"WA\"}}",
	"method": "GET",
	"orderNo": 1777186528033,
	"retryCount": 0,
	"uniqueKey": "https://skagit.craigslist.org/search/sss?query=yard+sale+garage+sale&s=480",
	"url": "https://skagit.craigslist.org/search/sss?query=yard+sale+garage+sale&s=480"
}