{
	"id": "azROaLoZUjeq96O",
	"json": "{\"id\":\"azROaLoZUjeq96O\",\"url\":\"https://rockford.craigslist.org/search/sss?query=yard+sale+garage+sale&s=480\",\"uniqueKey\":\"https://rockford.craigslist.org/search/sss?query=yard+sale+garage+sale&s=480\",\"method\":\"GET\",\"noRetry\":false,\"retryCount\":0,\"errorMessages\":[],\"headers\":{},\"userData\":{\"source\":\"craigslist\",\"state\":\"IL\"}}",
	"method": "GET",
	"orderNo": 1777186518192,
	"retryCount": 0,
	"uniqueKey": "https://rockford.craigslist.org/search/sss?query=yard+sale+garage+sale&s=480",
	"url": "https://rockford.craigslist.org/search/sss?query=yard+sale+garage+sale&s=480"
}