{
	"id": "CIlgXHlRBGnj5Ao",
	"json": "{\"id\":\"CIlgXHlRBGnj5Ao\",\"url\":\"https://fortsmith.craigslist.org/search/gms?s=240\",\"uniqueKey\":\"https://fortsmith.craigslist.org/search/gms?s=240\",\"method\":\"GET\",\"noRetry\":false,\"retryCount\":0,\"errorMessages\":[],\"headers\":{},\"userData\":{\"source\":\"craigslist\",\"state\":\"AR\",\"pageType\":\"index\"}}",
	"method": "GET",
	"orderNo": 1777040323070,
	"retryCount": 0,
	"uniqueKey": "https://fortsmith.craigslist.org/search/gms?s=240",
	"url": "https://fortsmith.craigslist.org/search/gms?s=240"
}