{
	"id": "cK7UhozarZNhi36",
	"json": "{\"id\":\"cK7UhozarZNhi36\",\"url\":\"https://charlotte.craigslist.org/search/ccc?query=yard+sale\",\"uniqueKey\":\"https://charlotte.craigslist.org/search/ccc?query=yard+sale\",\"method\":\"GET\",\"noRetry\":false,\"retryCount\":0,\"errorMessages\":[],\"headers\":{},\"userData\":{\"source\":\"craigslist\",\"state\":\"NC\"}}",
	"method": "GET",
	"orderNo": 1777186523422,
	"retryCount": 0,
	"uniqueKey": "https://charlotte.craigslist.org/search/ccc?query=yard+sale",
	"url": "https://charlotte.craigslist.org/search/ccc?query=yard+sale"
}