{
	"id": "d6mTdfZbX6X1Xcq",
	"json": "{\"id\":\"d6mTdfZbX6X1Xcq\",\"url\":\"https://newjersey.craigslist.org/search/gms\",\"uniqueKey\":\"https://newjersey.craigslist.org/search/gms\",\"method\":\"GET\",\"noRetry\":false,\"retryCount\":0,\"errorMessages\":[],\"headers\":{},\"userData\":{\"source\":\"craigslist\",\"state\":\"NJ\",\"pageType\":\"index\"}}",
	"method": "GET",
	"orderNo": 1777040325772,
	"retryCount": 0,
	"uniqueKey": "https://newjersey.craigslist.org/search/gms",
	"url": "https://newjersey.craigslist.org/search/gms"
}