{
	"id": "e2DDDVz8nabFjHE",
	"json": "{\"id\":\"e2DDDVz8nabFjHE\",\"url\":\"https://asheville.craigslist.org/search/gms?s=240\",\"uniqueKey\":\"https://asheville.craigslist.org/search/gms?s=240\",\"method\":\"GET\",\"noRetry\":false,\"retryCount\":0,\"errorMessages\":[],\"headers\":{},\"userData\":{\"source\":\"craigslist\",\"state\":\"NC\"}}",
	"method": "GET",
	"orderNo": 1777186523373,
	"retryCount": 0,
	"uniqueKey": "https://asheville.craigslist.org/search/gms?s=240",
	"url": "https://asheville.craigslist.org/search/gms?s=240"
}