{
	"id": "eZG02cEx0whL9RA",
	"json": "{\"id\":\"eZG02cEx0whL9RA\",\"url\":\"https://washingtondc.craigslist.org/nva/gms/d/falls-church-big-garage-sale/7924264355.html\",\"loadedUrl\":\"https://washingtondc.craigslist.org/nva/gms/d/falls-church-big-garage-sale/7924264355.html\",\"uniqueKey\":\"https://washingtondc.craigslist.org/nva/gms/d/falls-church-big-garage-sale/7924264355.html\",\"method\":\"GET\",\"noRetry\":false,\"retryCount\":0,\"errorMessages\":[],\"headers\":{},\"userData\":{\"source\":\"craigslist\",\"state\":\"DC\",\"handler\":\"detail\",\"__crawlee\":{\"state\":4}},\"handledAt\":\"2026-04-26T13:28:31.482Z\"}",
	"method": "GET",
	"orderNo": null,
	"retryCount": 0,
	"uniqueKey": "https://washingtondc.craigslist.org/nva/gms/d/falls-church-big-garage-sale/7924264355.html",
	"url": "https://washingtondc.craigslist.org/nva/gms/d/falls-church-big-garage-sale/7924264355.html"
}