{
	"id": "g8szIL6pEnXhSSs",
	"json": "{\"id\":\"g8szIL6pEnXhSSs\",\"url\":\"https://humboldt.craigslist.org/gms/d/fortuna-yard-sale/7929784886.html\",\"loadedUrl\":\"https://humboldt.craigslist.org/gms/d/fortuna-yard-sale/7929784886.html\",\"uniqueKey\":\"https://humboldt.craigslist.org/gms/d/fortuna-yard-sale/7929784886.html\",\"method\":\"GET\",\"noRetry\":false,\"retryCount\":0,\"errorMessages\":[],\"headers\":{},\"userData\":{\"source\":\"craigslist\",\"state\":\"CA\",\"handler\":\"detail\",\"__crawlee\":{\"state\":4}},\"handledAt\":\"2026-04-26T08:57:11.391Z\"}",
	"method": "GET",
	"orderNo": null,
	"retryCount": 0,
	"uniqueKey": "https://humboldt.craigslist.org/gms/d/fortuna-yard-sale/7929784886.html",
	"url": "https://humboldt.craigslist.org/gms/d/fortuna-yard-sale/7929784886.html"
}