{
	"id": "Gbg58V3fZDFFbBi",
	"json": "{\"id\":\"Gbg58V3fZDFFbBi\",\"url\":\"https://www.yardsalesearch.com/garage-sales-in-Henderson-NV.html\",\"uniqueKey\":\"https://www.yardsalesearch.com/garage-sales-in-Henderson-NV.html\",\"method\":\"GET\",\"noRetry\":false,\"retryCount\":0,\"errorMessages\":[],\"headers\":{},\"userData\":{\"source\":\"yardsalesearch\",\"state\":\"NV\",\"pageType\":\"index\"}}",
	"method": "GET",
	"orderNo": 1776804013046,
	"retryCount": 0,
	"uniqueKey": "https://www.yardsalesearch.com/garage-sales-in-Henderson-NV.html",
	"url": "https://www.yardsalesearch.com/garage-sales-in-Henderson-NV.html"
}