{
	"id": "gC4KeA9G6Sfdgrm",
	"json": "{\"id\":\"gC4KeA9G6Sfdgrm\",\"url\":\"https://richmondin.craigslist.org/search/gms?s=360\",\"uniqueKey\":\"https://richmondin.craigslist.org/search/gms?s=360\",\"method\":\"GET\",\"noRetry\":false,\"retryCount\":0,\"errorMessages\":[],\"headers\":{},\"userData\":{\"source\":\"craigslist\",\"state\":\"IN\"}}",
	"method": "GET",
	"orderNo": 1777186518353,
	"retryCount": 0,
	"uniqueKey": "https://richmondin.craigslist.org/search/gms?s=360",
	"url": "https://richmondin.craigslist.org/search/gms?s=360"
}