{
	"id": "h9aPK32Dc8b259y",
	"json": "{\"id\":\"h9aPK32Dc8b259y\",\"url\":\"https://www.estatesales.net/estate-sales/Georgia?page=3\",\"uniqueKey\":\"https://www.estatesales.net/estate-sales/Georgia?page=3\",\"method\":\"GET\",\"noRetry\":false,\"retryCount\":0,\"errorMessages\":[],\"headers\":{},\"userData\":{\"source\":\"estatesales\",\"state\":\"Georgia\"}}",
	"method": "GET",
	"orderNo": 1777186528598,
	"retryCount": 0,
	"uniqueKey": "https://www.estatesales.net/estate-sales/Georgia?page=3",
	"url": "https://www.estatesales.net/estate-sales/Georgia?page=3"
}