{
	"id": "HN9JRQK3VzYXzu4",
	"json": "{\"id\":\"HN9JRQK3VzYXzu4\",\"url\":\"https://texoma.craigslist.org/search/sss?query=yard+sale+garage+sale\",\"uniqueKey\":\"https://texoma.craigslist.org/search/sss?query=yard+sale+garage+sale\",\"method\":\"GET\",\"noRetry\":false,\"retryCount\":0,\"errorMessages\":[],\"headers\":{},\"userData\":{\"source\":\"craigslist\",\"state\":\"TX\"}}",
	"method": "GET",
	"orderNo": 1777186527569,
	"retryCount": 0,
	"uniqueKey": "https://texoma.craigslist.org/search/sss?query=yard+sale+garage+sale",
	"url": "https://texoma.craigslist.org/search/sss?query=yard+sale+garage+sale"
}