{
	"id": "HRNuvNNuKWOycmQ",
	"json": "{\"id\":\"HRNuvNNuKWOycmQ\",\"url\":\"https://atlanta.craigslist.org/search/gms?s=240\",\"uniqueKey\":\"https://atlanta.craigslist.org/search/gms?s=240\",\"method\":\"GET\",\"noRetry\":false,\"retryCount\":0,\"errorMessages\":[],\"headers\":{},\"userData\":{\"source\":\"craigslist\",\"state\":\"GA\",\"pageType\":\"index\"}}",
	"method": "GET",
	"orderNo": 1777040323707,
	"retryCount": 0,
	"uniqueKey": "https://atlanta.craigslist.org/search/gms?s=240",
	"url": "https://atlanta.craigslist.org/search/gms?s=240"
}