{
	"id": "iKvaVq8MOkSIJdb",
	"json": "{\"id\":\"iKvaVq8MOkSIJdb\",\"url\":\"https://racine.craigslist.org/search/gms?s=480\",\"uniqueKey\":\"https://racine.craigslist.org/search/gms?s=480\",\"method\":\"GET\",\"noRetry\":false,\"retryCount\":0,\"errorMessages\":[],\"headers\":{},\"userData\":{\"source\":\"craigslist\",\"state\":\"WI\"}}",
	"method": "GET",
	"orderNo": 1777186528429,
	"retryCount": 0,
	"uniqueKey": "https://racine.craigslist.org/search/gms?s=480",
	"url": "https://racine.craigslist.org/search/gms?s=480"
}