{
	"id": "ioNMP1puGaFVX1N",
	"json": "{\"id\":\"ioNMP1puGaFVX1N\",\"url\":\"https://sacramento.craigslist.org/gms/d/rancho-cordova-moving-sale/7927182005.html\",\"loadedUrl\":\"https://sacramento.craigslist.org/gms/d/rancho-cordova-moving-sale/7927182005.html\",\"uniqueKey\":\"https://sacramento.craigslist.org/gms/d/rancho-cordova-moving-sale/7927182005.html\",\"method\":\"GET\",\"noRetry\":false,\"retryCount\":0,\"errorMessages\":[],\"headers\":{},\"userData\":{\"source\":\"craigslist\",\"state\":\"CA\",\"handler\":\"detail\",\"__crawlee\":{\"state\":4}},\"handledAt\":\"2026-04-26T10:51:19.172Z\"}",
	"method": "GET",
	"orderNo": null,
	"retryCount": 0,
	"uniqueKey": "https://sacramento.craigslist.org/gms/d/rancho-cordova-moving-sale/7927182005.html",
	"url": "https://sacramento.craigslist.org/gms/d/rancho-cordova-moving-sale/7927182005.html"
}