{
	"id": "iyU5J7evJH3GVjJ",
	"json": "{\"id\":\"iyU5J7evJH3GVjJ\",\"url\":\"https://www.yardsalesearch.com/garage-sales-in-Lexington-KY.html?page=3\",\"uniqueKey\":\"https://www.yardsalesearch.com/garage-sales-in-Lexington-KY.html?page=3\",\"method\":\"GET\",\"noRetry\":false,\"retryCount\":0,\"errorMessages\":[],\"headers\":{},\"userData\":{\"source\":\"yardsalesearch\",\"state\":\"KY\",\"pageType\":\"index\"}}",
	"method": "GET",
	"orderNo": 1776804012766,
	"retryCount": 0,
	"uniqueKey": "https://www.yardsalesearch.com/garage-sales-in-Lexington-KY.html?page=3",
	"url": "https://www.yardsalesearch.com/garage-sales-in-Lexington-KY.html?page=3"
}