{
	"id": "J8TIDThbSkHLNdP",
	"json": "{\"id\":\"J8TIDThbSkHLNdP\",\"url\":\"https://syracuse.craigslist.org/search/gms?s=480\",\"uniqueKey\":\"https://syracuse.craigslist.org/search/gms?s=480\",\"method\":\"GET\",\"noRetry\":false,\"retryCount\":0,\"errorMessages\":[],\"headers\":{},\"userData\":{\"source\":\"craigslist\",\"state\":\"NY\"}}",
	"method": "GET",
	"orderNo": 1777186523324,
	"retryCount": 0,
	"uniqueKey": "https://syracuse.craigslist.org/search/gms?s=480",
	"url": "https://syracuse.craigslist.org/search/gms?s=480"
}