{
	"id": "jdZQb3e2yS3kxPf",
	"json": "{\"id\":\"jdZQb3e2yS3kxPf\",\"url\":\"https://gadsden.craigslist.org/search/gms?s=360\",\"loadedUrl\":\"https://gadsden.craigslist.org/search/gms?s=360\",\"uniqueKey\":\"https://gadsden.craigslist.org/search/gms?s=360\",\"method\":\"GET\",\"noRetry\":false,\"retryCount\":0,\"errorMessages\":[],\"headers\":{},\"userData\":{\"source\":\"craigslist\",\"state\":\"AL\",\"__crawlee\":{\"state\":4}},\"handledAt\":\"2026-04-26T07:00:35.139Z\"}",
	"method": "GET",
	"orderNo": null,
	"retryCount": 0,
	"uniqueKey": "https://gadsden.craigslist.org/search/gms?s=360",
	"url": "https://gadsden.craigslist.org/search/gms?s=360"
}