{
	"id": "jLR7NZ344am5o2E",
	"json": "{\"id\":\"jLR7NZ344am5o2E\",\"url\":\"https://www.yardsalesearch.com/garage-sales-in-Chesapeake-VA.html\",\"uniqueKey\":\"https://www.yardsalesearch.com/garage-sales-in-Chesapeake-VA.html\",\"method\":\"GET\",\"noRetry\":false,\"retryCount\":0,\"errorMessages\":[],\"headers\":{},\"userData\":{\"source\":\"yardsalesearch\",\"state\":\"VA\",\"pageType\":\"index\"}}",
	"method": "GET",
	"orderNo": 1776804014683,
	"retryCount": 0,
	"uniqueKey": "https://www.yardsalesearch.com/garage-sales-in-Chesapeake-VA.html",
	"url": "https://www.yardsalesearch.com/garage-sales-in-Chesapeake-VA.html"
}