{
	"id": "JQ50oJeXt91ojQO",
	"json": "{\"id\":\"JQ50oJeXt91ojQO\",\"url\":\"https://scottsbluff.craigslist.org/search/gms\",\"uniqueKey\":\"https://scottsbluff.craigslist.org/search/gms\",\"method\":\"GET\",\"noRetry\":false,\"retryCount\":0,\"errorMessages\":[],\"headers\":{},\"userData\":{\"source\":\"craigslist\",\"state\":\"NE\"}}",
	"method": "GET",
	"orderNo": 1777186522689,
	"retryCount": 0,
	"uniqueKey": "https://scottsbluff.craigslist.org/search/gms",
	"url": "https://scottsbluff.craigslist.org/search/gms"
}