{
	"id": "LxHmespbGd69IEe",
	"json": "{\"id\":\"LxHmespbGd69IEe\",\"url\":\"https://swks.craigslist.org/search/sss?query=estate+sale\",\"uniqueKey\":\"https://swks.craigslist.org/search/sss?query=estate+sale\",\"method\":\"GET\",\"noRetry\":false,\"retryCount\":0,\"errorMessages\":[],\"headers\":{},\"userData\":{\"source\":\"craigslist\",\"state\":\"KS\",\"pageType\":\"index\"}}",
	"method": "GET",
	"orderNo": 1777040324443,
	"retryCount": 0,
	"uniqueKey": "https://swks.craigslist.org/search/sss?query=estate+sale",
	"url": "https://swks.craigslist.org/search/sss?query=estate+sale"
}