{
	"id": "MeNBHaWVqlKtsF6",
	"json": "{\"id\":\"MeNBHaWVqlKtsF6\",\"url\":\"https://ocala.craigslist.org/gms/d/leesburg-big-yard-sale/7928927197.html\",\"loadedUrl\":\"https://ocala.craigslist.org/gms/d/leesburg-big-yard-sale/7928927197.html\",\"uniqueKey\":\"https://ocala.craigslist.org/gms/d/leesburg-big-yard-sale/7928927197.html\",\"method\":\"GET\",\"noRetry\":false,\"retryCount\":0,\"errorMessages\":[],\"headers\":{},\"userData\":{\"source\":\"craigslist\",\"state\":\"FL\",\"handler\":\"detail\",\"__crawlee\":{\"state\":4}},\"handledAt\":\"2026-04-26T14:59:58.694Z\"}",
	"method": "GET",
	"orderNo": null,
	"retryCount": 0,
	"uniqueKey": "https://ocala.craigslist.org/gms/d/leesburg-big-yard-sale/7928927197.html",
	"url": "https://ocala.craigslist.org/gms/d/leesburg-big-yard-sale/7928927197.html"
}