{
	"id": "MFfigIUQCiXJYbU",
	"json": "{\"id\":\"MFfigIUQCiXJYbU\",\"url\":\"https://porthuron.craigslist.org/search/gms?s=480\",\"uniqueKey\":\"https://porthuron.craigslist.org/search/gms?s=480\",\"method\":\"GET\",\"noRetry\":false,\"retryCount\":0,\"errorMessages\":[],\"headers\":{},\"userData\":{\"source\":\"craigslist\",\"state\":\"MI\"}}",
	"method": "GET",
	"orderNo": 1777186520867,
	"retryCount": 0,
	"uniqueKey": "https://porthuron.craigslist.org/search/gms?s=480",
	"url": "https://porthuron.craigslist.org/search/gms?s=480"
}