{
	"id": "nJ1uDrglbZv7I9X",
	"json": "{\"id\":\"nJ1uDrglbZv7I9X\",\"url\":\"https://sfbay.craigslist.org/sby/gms/d/saratoga-estate-sale/7925302321.html\",\"loadedUrl\":\"https://sfbay.craigslist.org/sby/gms/d/saratoga-estate-sale/7925302321.html\",\"uniqueKey\":\"https://sfbay.craigslist.org/sby/gms/d/saratoga-estate-sale/7925302321.html\",\"method\":\"GET\",\"noRetry\":false,\"retryCount\":0,\"errorMessages\":[],\"headers\":{},\"userData\":{\"source\":\"craigslist\",\"state\":\"CA\",\"handler\":\"detail\",\"__crawlee\":{\"state\":4}},\"handledAt\":\"2026-04-26T11:26:06.717Z\"}",
	"method": "GET",
	"orderNo": null,
	"retryCount": 0,
	"uniqueKey": "https://sfbay.craigslist.org/sby/gms/d/saratoga-estate-sale/7925302321.html",
	"url": "https://sfbay.craigslist.org/sby/gms/d/saratoga-estate-sale/7925302321.html"
}