{
	"id": "nwteYxeZVZ4zwHe",
	"json": "{\"id\":\"nwteYxeZVZ4zwHe\",\"url\":\"https://merced.craigslist.org/gms/d/atwater-yard-sale/7928588347.html\",\"loadedUrl\":\"https://merced.craigslist.org/gms/d/atwater-yard-sale/7928588347.html\",\"uniqueKey\":\"https://merced.craigslist.org/gms/d/atwater-yard-sale/7928588347.html\",\"method\":\"GET\",\"noRetry\":false,\"retryCount\":0,\"errorMessages\":[],\"headers\":{},\"userData\":{\"source\":\"craigslist\",\"state\":\"CA\",\"handler\":\"detail\",\"__crawlee\":{\"state\":4}},\"handledAt\":\"2026-04-26T09:50:36.876Z\"}",
	"method": "GET",
	"orderNo": null,
	"retryCount": 0,
	"uniqueKey": "https://merced.craigslist.org/gms/d/atwater-yard-sale/7928588347.html",
	"url": "https://merced.craigslist.org/gms/d/atwater-yard-sale/7928588347.html"
}