{
	"id": "o102WFnWHYJePC4",
	"json": "{\"id\":\"o102WFnWHYJePC4\",\"url\":\"https://monterey.craigslist.org/gms/d/pacific-grove-moving-sale/7921313772.html\",\"loadedUrl\":\"https://monterey.craigslist.org/gms/d/pacific-grove-moving-sale/7921313772.html\",\"uniqueKey\":\"https://monterey.craigslist.org/gms/d/pacific-grove-moving-sale/7921313772.html\",\"method\":\"GET\",\"noRetry\":false,\"retryCount\":0,\"errorMessages\":[],\"headers\":{},\"userData\":{\"source\":\"craigslist\",\"state\":\"CA\",\"handler\":\"detail\",\"__crawlee\":{\"state\":4}},\"handledAt\":\"2026-04-26T10:04:46.787Z\"}",
	"method": "GET",
	"orderNo": null,
	"retryCount": 0,
	"uniqueKey": "https://monterey.craigslist.org/gms/d/pacific-grove-moving-sale/7921313772.html",
	"url": "https://monterey.craigslist.org/gms/d/pacific-grove-moving-sale/7921313772.html"
}