{
	"id": "oIKuQzYsIVXCfRY",
	"json": "{\"id\":\"oIKuQzYsIVXCfRY\",\"url\":\"https://athensga.craigslist.org/search/ccc?query=garage+sale\",\"uniqueKey\":\"https://athensga.craigslist.org/search/ccc?query=garage+sale\",\"method\":\"GET\",\"noRetry\":false,\"retryCount\":0,\"errorMessages\":[],\"headers\":{},\"userData\":{\"source\":\"craigslist\",\"state\":\"GA\"}}",
	"method": "GET",
	"orderNo": 1777186517419,
	"retryCount": 0,
	"uniqueKey": "https://athensga.craigslist.org/search/ccc?query=garage+sale",
	"url": "https://athensga.craigslist.org/search/ccc?query=garage+sale"
}