{
	"id": "PW6DcOsFI2duYOx",
	"json": "{\"id\":\"PW6DcOsFI2duYOx\",\"url\":\"https://sacramento.craigslist.org/search/gms?s=120\",\"loadedUrl\":\"https://sacramento.craigslist.org/search/gms?s=120\",\"uniqueKey\":\"https://sacramento.craigslist.org/search/gms?s=120\",\"method\":\"GET\",\"noRetry\":false,\"retryCount\":0,\"errorMessages\":[],\"headers\":{},\"userData\":{\"source\":\"craigslist\",\"state\":\"CA\",\"__crawlee\":{\"state\":4}},\"handledAt\":\"2026-04-26T10:39:56.086Z\"}",
	"method": "GET",
	"orderNo": null,
	"retryCount": 0,
	"uniqueKey": "https://sacramento.craigslist.org/search/gms?s=120",
	"url": "https://sacramento.craigslist.org/search/gms?s=120"
}