{
	"id": "QiscuSdVI16zUQX",
	"json": "{\"id\":\"QiscuSdVI16zUQX\",\"url\":\"https://rockies.craigslist.org/search/sss?query=yard+sale+garage+sale\",\"loadedUrl\":\"https://rockies.craigslist.org/search/sss?query=yard+sale+garage+sale\",\"uniqueKey\":\"https://rockies.craigslist.org/search/sss?query=yard+sale+garage+sale\",\"method\":\"GET\",\"noRetry\":false,\"retryCount\":0,\"errorMessages\":[],\"headers\":{},\"userData\":{\"source\":\"craigslist\",\"state\":\"CO\",\"__crawlee\":{\"state\":4}},\"handledAt\":\"2026-04-26T12:53:44.533Z\"}",
	"method": "GET",
	"orderNo": null,
	"retryCount": 0,
	"uniqueKey": "https://rockies.craigslist.org/search/sss?query=yard+sale+garage+sale",
	"url": "https://rockies.craigslist.org/search/sss?query=yard+sale+garage+sale"
}