{
	"id": "TicRmz9ykd9yryY",
	"json": "{\"id\":\"TicRmz9ykd9yryY\",\"url\":\"https://pueblo.craigslist.org/gms/d/pueblo-garage-sale/7925365592.html\",\"loadedUrl\":\"https://pueblo.craigslist.org/gms/d/pueblo-garage-sale/7925365592.html\",\"uniqueKey\":\"https://pueblo.craigslist.org/gms/d/pueblo-garage-sale/7925365592.html\",\"method\":\"GET\",\"noRetry\":false,\"retryCount\":0,\"errorMessages\":[],\"headers\":{},\"userData\":{\"source\":\"craigslist\",\"state\":\"CO\",\"handler\":\"detail\",\"__crawlee\":{\"state\":4}},\"handledAt\":\"2026-04-26T12:57:35.049Z\"}",
	"method": "GET",
	"orderNo": null,
	"retryCount": 0,
	"uniqueKey": "https://pueblo.craigslist.org/gms/d/pueblo-garage-sale/7925365592.html",
	"url": "https://pueblo.craigslist.org/gms/d/pueblo-garage-sale/7925365592.html"
}