{
	"id": "ty3z3Id8YPmaCRK",
	"json": "{\"id\":\"ty3z3Id8YPmaCRK\",\"url\":\"https://www.yardsalesearch.com/yard-sales/Nashua-NH.html\",\"uniqueKey\":\"https://www.yardsalesearch.com/yard-sales/Nashua-NH.html\",\"method\":\"GET\",\"noRetry\":false,\"retryCount\":0,\"errorMessages\":[],\"headers\":{},\"userData\":{\"source\":\"yardsalesearch\",\"state\":\"NH\",\"yssSlug\":\"Nashua-NH\"}}",
	"method": "GET",
	"orderNo": 1777186532406,
	"retryCount": 0,
	"uniqueKey": "https://www.yardsalesearch.com/yard-sales/Nashua-NH.html",
	"url": "https://www.yardsalesearch.com/yard-sales/Nashua-NH.html"
}