{
	"id": "U8kQ3xzSurIQxsW",
	"json": "{\"id\":\"U8kQ3xzSurIQxsW\",\"url\":\"https://www.yardsalesearch.com/yard-sales/Anchorage-AK.html\",\"uniqueKey\":\"https://www.yardsalesearch.com/yard-sales/Anchorage-AK.html\",\"method\":\"GET\",\"noRetry\":false,\"retryCount\":0,\"errorMessages\":[],\"headers\":{},\"userData\":{\"source\":\"yardsalesearch\",\"state\":\"AK\",\"yssSlug\":\"Anchorage-AK\"}}",
	"method": "GET",
	"orderNo": 1777186530334,
	"retryCount": 0,
	"uniqueKey": "https://www.yardsalesearch.com/yard-sales/Anchorage-AK.html",
	"url": "https://www.yardsalesearch.com/yard-sales/Anchorage-AK.html"
}