{
	"id": "UHXIxneLLg5ZzxN",
	"json": "{\"id\":\"UHXIxneLLg5ZzxN\",\"url\":\"https://chicago.craigslist.org/search/ccc?query=garage+sale\",\"uniqueKey\":\"https://chicago.craigslist.org/search/ccc?query=garage+sale\",\"method\":\"GET\",\"noRetry\":false,\"retryCount\":0,\"errorMessages\":[],\"headers\":{},\"userData\":{\"source\":\"craigslist\",\"state\":\"IL\"}}",
	"method": "GET",
	"orderNo": 1777186518109,
	"retryCount": 0,
	"uniqueKey": "https://chicago.craigslist.org/search/ccc?query=garage+sale",
	"url": "https://chicago.craigslist.org/search/ccc?query=garage+sale"
}