{
	"id": "V0r9aYrSTgU06It",
	"json": "{\"id\":\"V0r9aYrSTgU06It\",\"url\":\"https://pullman.craigslist.org/search/ccc?query=garage+sale\",\"uniqueKey\":\"https://pullman.craigslist.org/search/ccc?query=garage+sale\",\"method\":\"GET\",\"noRetry\":false,\"retryCount\":0,\"errorMessages\":[],\"headers\":{},\"userData\":{\"source\":\"craigslist\",\"state\":\"WA\"}}",
	"method": "GET",
	"orderNo": 1777186528009,
	"retryCount": 0,
	"uniqueKey": "https://pullman.craigslist.org/search/ccc?query=garage+sale",
	"url": "https://pullman.craigslist.org/search/ccc?query=garage+sale"
}