{
	"id": "v0UQNoHDdC9MYrA",
	"json": "{\"id\":\"v0UQNoHDdC9MYrA\",\"url\":\"https://lakeland.craigslist.org/for/d/lakeland-estate-sale-yard-signs/7914525523.html\",\"loadedUrl\":\"https://lakeland.craigslist.org/for/d/lakeland-estate-sale-yard-signs/7914525523.html\",\"uniqueKey\":\"https://lakeland.craigslist.org/for/d/lakeland-estate-sale-yard-signs/7914525523.html\",\"method\":\"GET\",\"noRetry\":false,\"retryCount\":0,\"errorMessages\":[],\"headers\":{},\"userData\":{\"source\":\"craigslist\",\"state\":\"FL\",\"handler\":\"detail\",\"__crawlee\":{\"state\":4}},\"handledAt\":\"2026-04-26T14:48:39.124Z\"}",
	"method": "GET",
	"orderNo": null,
	"retryCount": 0,
	"uniqueKey": "https://lakeland.craigslist.org/for/d/lakeland-estate-sale-yard-signs/7914525523.html",
	"url": "https://lakeland.craigslist.org/for/d/lakeland-estate-sale-yard-signs/7914525523.html"
}