{
	"id": "WOixKMf3yjXS3PN",
	"json": "{\"id\":\"WOixKMf3yjXS3PN\",\"url\":\"https://jxn.craigslist.org/search/sss?query=moving+sale\",\"uniqueKey\":\"https://jxn.craigslist.org/search/sss?query=moving+sale\",\"method\":\"GET\",\"noRetry\":false,\"retryCount\":0,\"errorMessages\":[],\"headers\":{},\"userData\":{\"source\":\"craigslist\",\"state\":\"MI\"}}",
	"method": "GET",
	"orderNo": 1777186520753,
	"retryCount": 0,
	"uniqueKey": "https://jxn.craigslist.org/search/sss?query=moving+sale",
	"url": "https://jxn.craigslist.org/search/sss?query=moving+sale"
}