{
	"id": "Wow0zmiWyajFkQF",
	"json": "{\"id\":\"Wow0zmiWyajFkQF\",\"url\":\"https://yuma.craigslist.org/gms/d/yuma-estate-sale/7922422951.html\",\"loadedUrl\":\"https://yuma.craigslist.org/gms/d/yuma-estate-sale/7922422951.html\",\"uniqueKey\":\"https://yuma.craigslist.org/gms/d/yuma-estate-sale/7922422951.html\",\"method\":\"GET\",\"noRetry\":false,\"retryCount\":0,\"errorMessages\":[],\"headers\":{},\"userData\":{\"source\":\"craigslist\",\"state\":\"AZ\",\"handler\":\"detail\",\"__crawlee\":{\"state\":4}},\"handledAt\":\"2026-04-26T08:09:51.112Z\"}",
	"method": "GET",
	"orderNo": null,
	"retryCount": 0,
	"uniqueKey": "https://yuma.craigslist.org/gms/d/yuma-estate-sale/7922422951.html",
	"url": "https://yuma.craigslist.org/gms/d/yuma-estate-sale/7922422951.html"
}