{
	"id": "XxxdtTbdX0ZJKLJ",
	"json": "{\"id\":\"XxxdtTbdX0ZJKLJ\",\"url\":\"https://tuscaloosa.craigslist.org/search/sss?query=yard+sale+garage+sale\",\"loadedUrl\":\"https://tuscaloosa.craigslist.org/search/sss?query=yard+sale+garage+sale\",\"uniqueKey\":\"https://tuscaloosa.craigslist.org/search/sss?query=yard+sale+garage+sale\",\"method\":\"GET\",\"noRetry\":false,\"retryCount\":0,\"errorMessages\":[],\"headers\":{},\"userData\":{\"source\":\"craigslist\",\"state\":\"AL\",\"__crawlee\":{\"state\":4}},\"handledAt\":\"2026-04-26T07:09:18.166Z\"}",
	"method": "GET",
	"orderNo": null,
	"retryCount": 0,
	"uniqueKey": "https://tuscaloosa.craigslist.org/search/sss?query=yard+sale+garage+sale",
	"url": "https://tuscaloosa.craigslist.org/search/sss?query=yard+sale+garage+sale"
}