{
	"id": "y9Ivtvt1hAogUNP",
	"json": "{\"id\":\"y9Ivtvt1hAogUNP\",\"url\":\"https://visalia.craigslist.org/hsh/d/springville-yard-estate-sale/7929798810.html\",\"loadedUrl\":\"https://visalia.craigslist.org/hsh/d/springville-yard-estate-sale/7929798810.html\",\"uniqueKey\":\"https://visalia.craigslist.org/hsh/d/springville-yard-estate-sale/7929798810.html\",\"method\":\"GET\",\"noRetry\":false,\"retryCount\":0,\"errorMessages\":[],\"headers\":{},\"userData\":{\"source\":\"craigslist\",\"state\":\"CA\",\"handler\":\"detail\",\"__crawlee\":{\"state\":4}},\"handledAt\":\"2026-04-26T12:22:41.932Z\"}",
	"method": "GET",
	"orderNo": null,
	"retryCount": 0,
	"uniqueKey": "https://visalia.craigslist.org/hsh/d/springville-yard-estate-sale/7929798810.html",
	"url": "https://visalia.craigslist.org/hsh/d/springville-yard-estate-sale/7929798810.html"
}