{
	"id": "zCUIgybnJZ79ODX",
	"json": "{\"id\":\"zCUIgybnJZ79ODX\",\"url\":\"https://fortdodge.craigslist.org/search/gms\",\"uniqueKey\":\"https://fortdodge.craigslist.org/search/gms\",\"method\":\"GET\",\"noRetry\":false,\"retryCount\":0,\"errorMessages\":[],\"headers\":{},\"userData\":{\"source\":\"craigslist\",\"state\":\"IA\",\"pageType\":\"index\"}}",
	"method": "GET",
	"orderNo": 1776804006642,
	"retryCount": 0,
	"uniqueKey": "https://fortdodge.craigslist.org/search/gms",
	"url": "https://fortdodge.craigslist.org/search/gms"
}