{
	"id": "ZMc5vfKpOg3ONrG",
	"json": "{\"id\":\"ZMc5vfKpOg3ONrG\",\"url\":\"https://sheboygan.craigslist.org/search/ccc?query=yard+sale\",\"uniqueKey\":\"https://sheboygan.craigslist.org/search/ccc?query=yard+sale\",\"method\":\"GET\",\"noRetry\":false,\"retryCount\":0,\"errorMessages\":[],\"headers\":{},\"userData\":{\"source\":\"craigslist\",\"state\":\"WI\"}}",
	"method": "GET",
	"orderNo": 1777186528466,
	"retryCount": 0,
	"uniqueKey": "https://sheboygan.craigslist.org/search/ccc?query=yard+sale",
	"url": "https://sheboygan.craigslist.org/search/ccc?query=yard+sale"
}