{
	"id": "zpCsqeiz6zNry0H",
	"json": "{\"id\":\"zpCsqeiz6zNry0H\",\"url\":\"https://hartford.craigslist.org/search/gms?s=120\",\"loadedUrl\":\"https://hartford.craigslist.org/search/gms?s=120\",\"uniqueKey\":\"https://hartford.craigslist.org/search/gms?s=120\",\"method\":\"GET\",\"noRetry\":false,\"retryCount\":0,\"errorMessages\":[],\"headers\":{},\"userData\":{\"source\":\"craigslist\",\"state\":\"CT\",\"__crawlee\":{\"state\":4}},\"handledAt\":\"2026-04-26T13:05:27.827Z\"}",
	"method": "GET",
	"orderNo": null,
	"retryCount": 0,
	"uniqueKey": "https://hartford.craigslist.org/search/gms?s=120",
	"url": "https://hartford.craigslist.org/search/gms?s=120"
}